dummyrest/__init__.py
dummyrest/app.py
dummyrest/db.py
dummyrest/models/__init__.py
dummyrest/models/author.py
dummyrest/models/book.py
dummyrest/resources/__init__.py
dummyrest/resources/author.py
dummyrest/resources/book.py
dummyrest/resources/dummyresource.py
dummyrest-0.1.1.data/scripts/dummyrest
dummyrest-0.1.1.data/scripts/dummyrest-nginx
dummyrest-0.1.1.dist-info/LICENSE
dummyrest-0.1.1.dist-info/METADATA
dummyrest-0.1.1.dist-info/WHEEL
dummyrest-0.1.1.dist-info/top_level.txt
dummyrest-0.1.1.dist-info/RECORD
