Metadata-Version: 2.1
Name: dummyrest
Version: 0.1.1
Summary: Dummy API for testing REST functions
Home-page: https://github.com/medianetlab/dummyrest.git
Author: Themis Anagnostopoulos
Author-email: thmanagnostopoulos@gmail.com
License: MIT
Platform: UNKNOWN
Classifier: License :: OSI Approved :: MIT License
Classifier: Programming Language :: Python
Classifier: Programming Language :: Python :: 3
Classifier: Programming Language :: Python :: 3.7
Classifier: Programming Language :: Python :: Implementation :: CPython
Classifier: Programming Language :: Python :: Implementation :: PyPy
Requires-Python: >=3.6.0
Requires-Dist: flask
Requires-Dist: flask-restful
Requires-Dist: gunicorn
Requires-Dist: flask-sqlalchemy
Requires-Dist: uwsgi
Requires-Dist: psycopg2-binary
